[
  {
    "Type": "BodySetup",
    "Name": "BodySetup_0",
    "Outer": "FireGroundSpot",
    "Class": "UScriptClass'BodySetup'",
    "Flags": "RF_Transactional | RF_WasLoaded | RF_LoadCompleted",
    "Properties": {
      "DefaultInstance": {
        "ObjectType": "ECollisionChannel::ECC_WorldStatic",
        "CollisionProfileName": "BlockAll"
      }
    },
    "BodySetupGuid": "35034EB94758360DCED3259F9B8E16B5",
    "CookedFormatData": {
      "PhysXPC": {
        "BulkDataFlags": "BULKDATA_SingleUse | BULKDATA_ForceInlinePayload",
        "ElementCount": 28,
        "SizeOnDisk": 28,
        "OffsetInFile": "0x2FDC"
      }
    }
  },
  {
    "Type": "NavCollision",
    "Name": "NavCollision_4",
    "Outer": "FireGroundSpot",
    "Class": "UScriptClass'NavCollision'",
    "Flags": "RF_Transactional | RF_WasLoaded | RF_LoadCompleted",
    "CookedFormatData": {
      "NavCollision_Chaos": {
        "BulkDataFlags": "BULKDATA_SingleUse | BULKDATA_ForceInlinePayload",
        "ElementCount": 21,
        "SizeOnDisk": 21,
        "OffsetInFile": "0x303A"
      }
    }
  },
  {
    "Type": "StaticMesh",
    "Name": "FireGroundSpot",
    "Class": "UScriptClass'StaticMesh'",
    "Flags": "RF_Public | RF_Standalone | RF_WasLoaded | RF_LoadCompleted",
    "Properties": {
      "StaticMaterials": [
        {
          "MaterialInterface": {
            "ObjectName": "Material'FireGround'",
            "ObjectPath": "Anvil/Content/FX/Materials/FireGround.0"
          },
          "MaterialSlotName": "WorldGridMaterial",
          "ImportedMaterialSlotName": "WorldGridMaterial",
          "UVChannelData": {
            "bInitialized": true,
            "bOverrideDensities": false,
            "LocalUVDensities": 108.61436,
            "LocalUVDensities[1]": 0.0,
            "LocalUVDensities[2]": 0.0,
            "LocalUVDensities[3]": 0.0
          }
        }
      ],
      "LightmapUVDensity": 108.61436,
      "LightMapResolution": 64,
      "ExtendedBounds": {
        "Origin": {
          "X": -0.97255707,
          "Y": 1.1635742,
          "Z": 1.3765901
        },
        "BoxExtent": {
          "X": 55.70729,
          "Y": 57.357197,
          "Z": 3.3008537
        },
        "SphereRadius": 59.52238845825195
      }
    },
    "BodySetup": {
      "ObjectName": "BodySetup'FireGroundSpot:BodySetup_0'",
      "ObjectPath": "Anvil/Content/FX/Meshes/FireGroundSpot.0"
    },
    "NavCollision": {
      "ObjectName": "NavCollision'FireGroundSpot:NavCollision_4'",
      "ObjectPath": "Anvil/Content/FX/Meshes/FireGroundSpot.1"
    },
    "LightingGuid": "1610A8CD-4DC4C7CA-94151E8E-76885BBE",
    "RenderData": {
      "LODs": [
        {
          "Sections": [
            {
              "MaterialIndex": 0,
              "FirstIndex": 0,
              "NumTriangles": 220,
              "MinVertexIndex": 0,
              "MaxVertexIndex": 120,
              "bEnableCollision": true,
              "bCastShadow": true,
              "bForceOpaque": false,
              "bVisibleInRayTracing": true
            }
          ],
          "MaxDeviation": 0.0,
          "PositionVertexBuffer": {
            "Stride": 12,
            "NumVertices": 121
          },
          "VertexBuffer": {
            "NumTexCoords": 1,
            "NumVertices": 121,
            "Strides": -1,
            "UseHighPrecisionTangentBasis": false,
            "UseFullPrecisionUVs": false
          },
          "ColorVertexBuffer": {
            "Stride": 0,
            "NumVertices": 0
          },
          "CardRepresentationData": {
            "Bounds": {
              "Min": {
                "X": -57.679848,
                "Y": -57.193623,
                "Z": -2.9242635
              },
              "Max": {
                "X": 55.734734,
                "Y": 59.52077,
                "Z": 5.677444
              },
              "IsValid": 1
            },
            "MaxLodLevel": 0,
            "bMostlyTwoSided": false,
            "CardBuildData": []
          }
        }
      ],
      "NaniteResources": {
        "RootData": null,
        "StreamablePages": {
          "BulkDataFlags": "BULKDATA_None",
          "ElementCount": 0,
          "SizeOnDisk": 0,
          "OffsetInFile": "0x51D4"
        },
        "ImposterAtlas": [],
        "HierarchyNodes": [],
        "HierarchyRootOffsets": [],
        "PageStreamingStates": [],
        "PageDependencies": [],
        "AssemblyTransforms": null,
        "MeshBounds": null,
        "NumRootPages": 0,
        "PositionPrecision": 0,
        "NormalPrecision": 0,
        "TangentPrecision": 0,
        "NumInputTriangles": 0,
        "NumInputVertices": 0,
        "NumInputMeshes": 0,
        "NumInputTexCoords": 0,
        "NumClusters": 0,
        "ResourceFlags": 0
      },
      "Bounds": {
        "Origin": {
          "X": -0.972559,
          "Y": 1.1635742,
          "Z": 1.3765903
        },
        "BoxExtent": {
          "X": 55.70729,
          "Y": 57.357197,
          "Z": 3.3008537
        },
        "SphereRadius": 59.52239
      },
      "bLODsShareStaticLighting": true,
      "ScreenSize": [
        2.0,
        0.0,
        0.0,
        0.0,
        0.0,
        0.0,
        0.0,
        0.0
      ]
    }
  }
]