[
  {
    "Type": "BlueprintGeneratedClass",
    "Name": "CabbagePlant_C",
    "Class": "UScriptClass'BlueprintGeneratedClass'",
    "SuperStruct": {
      "ObjectName": "Class'EntityTemplate'",
      "ObjectPath": "/Script/R2"
    },
    "ClassFlags": "CLASS_ReplicationDataIsSetUp | CLASS_CompiledFromBlueprint | CLASS_HasInstancedReference",
    "ClassWithin": {
      "ObjectName": "Class'Object'",
      "ObjectPath": "/Script/CoreUObject"
    },
    "ClassConfigName": "Engine",
    "bCooked": true,
    "ClassDefaultObject": {
      "ObjectName": "CabbagePlant_C'Default__CabbagePlant_C'",
      "ObjectPath": "Anvil/Content/Blueprints/EntityTemplates/Resources/Plants/CabbagePlant.2"
    },
    "EditorTags": {
      "BlueprintType": "BPTYPE_Normal"
    }
  },
  {
    "Type": "BoxCollisionProxyComponent",
    "Name": "BoxCollisionProxyComponent_0",
    "Outer": "Default__CabbagePlant_C",
    "Class": "UScriptClass'BoxCollisionProxyComponent'",
    "Properties": {
      "Position": {
        "X": 0.0,
        "Y": 0.0,
        "Z": 100.0
      },
      "Extents": {
        "X": 50.0,
        "Y": 50.0,
        "Z": 200.0
      },
      "SurfaceType": "EAnvilPhysicalSurfaceType::SurfaceTypeGrass",
      "CollisionMask": 16
    }
  },
  {
    "Type": "CabbagePlant_C",
    "Name": "Default__CabbagePlant_C",
    "Class": "BlueprintGeneratedClass'Anvil/Content/Blueprints/EntityTemplates/Resources/Plants/CabbagePlant.CabbagePlant_C'",
    "Properties": {
      "CodeNameString": "CabbagePlant",
      "CodeName": 818422426,
      "Components": [
        {
          "ObjectName": "ResourceProxyComponent'Default__CabbagePlant_C:ResourceProxyComponent_0'",
          "ObjectPath": "Anvil/Content/Blueprints/EntityTemplates/Resources/Plants/CabbagePlant.3"
        },
        {
          "ObjectName": "BoxCollisionProxyComponent'Default__CabbagePlant_C:BoxCollisionProxyComponent_0'",
          "ObjectPath": "Anvil/Content/Blueprints/EntityTemplates/Resources/Plants/CabbagePlant.1"
        }
      ],
      "VisActorClass": {
        "ObjectName": "BlueprintGeneratedClass'BPVisCabbagePlant_C'",
        "ObjectPath": "Anvil/Content/Blueprints/VisActors/Resources/Plants/BPVisCabbagePlant.0"
      }
    }
  },
  {
    "Type": "ResourceProxyComponent",
    "Name": "ResourceProxyComponent_0",
    "Outer": "Default__CabbagePlant_C",
    "Class": "UScriptClass'ResourceProxyComponent'",
    "Properties": {
      "HitPoints": 1,
      "RequiredTool": "EAnvilToolType::Scythe",
      "LootTable": [
        {
          "ItemToDrop": {
            "ItemType": {
              "ObjectName": "BlueprintGeneratedClass'ResourceCabbage_C'",
              "ObjectPath": "Anvil/Content/Blueprints/ItemTemplates/Resources/ResourceCabbage.0"
            },
            "ItemCodeName": 0,
            "Count": 1,
            "ItemFlags": 0
          },
          "NormalizedChanceToDrop": 1.0,
          "MinDurability": 100.0,
          "MaxDurability": 100.0
        },
        {
          "ItemToDrop": {
            "ItemType": {
              "ObjectName": "BlueprintGeneratedClass'CabbageSeed_C'",
              "ObjectPath": "Anvil/Content/Blueprints/ItemTemplates/Resources/CabbageSeed.0"
            },
            "ItemCodeName": 0,
            "Count": 1,
            "ItemFlags": 0
          },
          "NormalizedChanceToDrop": 0.33,
          "MinDurability": 100.0,
          "MaxDurability": 100.0
        }
      ]
    }
  }
]