[
  {
    "Type": "Material",
    "Name": "Wireframe",
    "Class": "UScriptClass'Material'",
    "Flags": "RF_Public | RF_Standalone | RF_Transactional | RF_WasLoaded | RF_LoadCompleted",
    "Properties": {
      "BlendMode": "EBlendMode::BLEND_Translucent",
      "Wireframe": true,
      "bCanMaskedBeAssumedOpaque": true,
      "StateId": "44032801-40871C9E-DDF68A82-F0085422"
    },
    "LoadedMaterialResources": [],
    "CachedExpressionData": {
      "RuntimeEntries": {
        "ParameterInfoSet": [
          {
            "Name": "Intensity",
            "Association": "EMaterialParameterAssociation::GlobalParameter",
            "Index": -1
          }
        ]
      },
      "RuntimeEntries[1]": {
        "ParameterInfoSet": [
          {
            "Name": "WireframeColour",
            "Association": "EMaterialParameterAssociation::GlobalParameter",
            "Index": -1
          }
        ]
      },
      "RuntimeEntries[2]": {
        "ParameterInfoSet": []
      },
      "RuntimeEntries[3]": {
        "ParameterInfoSet": []
      },
      "RuntimeEntries[4]": {
        "ParameterInfoSet": []
      },
      "RuntimeEntries[5]": {
        "ParameterInfoSet": []
      },
      "ScalarPrimitiveDataIndexValues": [
        -1
      ],
      "VectorPrimitiveDataIndexValues": [
        -1
      ],
      "ScalarValues": [
        1.0
      ],
      "VectorValues": [
        {
          "R": 0.35240495,
          "G": 0.87987983,
          "B": 1.0,
          "A": 1.0,
          "Hex": "A0F1FF"
        }
      ],
      "DoubleVectorValues": [],
      "TextureValues": [],
      "FontValues": [],
      "FontPageValues": [],
      "RuntimeVirtualTextureValues": [],
      "ReferencedTextures": [],
      "FunctionInfos": [],
      "ParameterCollectionInfos": [],
      "GrassTypes": [],
      "MaterialLayers": {
        "LayerS": [],
        "Blends": []
      },
      "DynamicParameterNames": [],
      "QualityLevelsUsed": [
        false,
        false,
        false,
        false
      ],
      "bHasMaterialLayers": false,
      "bHasRuntimeVirtualTextureOutput": false,
      "bHasSceneColor": false,
      "bHasPerInstanceCustomData": false,
      "bHasPerInstanceRandom": false,
      "bHasVertexInterpolator": false,
      "PropertyConnectedBitmask": 1
    }
  }
]